mdtree/__init__.py
mdtree/main.py
mdtree/mdutils.py
mdtree/parser.py
mdtree/static/css/base.css
mdtree/static/css/mdtree.min.css
mdtree/static/css/pygments.css
mdtree/static/html/template.html
mdtree/static/js/mdtree.min.js
mdtree_mermaid-0.8.0.data/scripts/mdtree
mdtree_mermaid-0.8.0.dist-info/METADATA
mdtree_mermaid-0.8.0.dist-info/WHEEL
mdtree_mermaid-0.8.0.dist-info/entry_points.txt
mdtree_mermaid-0.8.0.dist-info/top_level.txt
mdtree_mermaid-0.8.0.dist-info/RECORD
