Metadata-Version: 2.4
Name: mdtree-mermaid
Version: 0.8.0
Summary: Convert markdown to html with TOC(table of contents) and Mermaid diagram support
Home-page: https://github.com/ltto/mdtree
Author: menduo
Author-email: menduo <shimenduo@gmail.com>
License: MIT
Project-URL: Homepage, https://github.com/ltto/mdtree
Project-URL: Bug Reports, https://github.com/ltto/mdtree/issues
Project-URL: Source, https://github.com/ltto/mdtree
Keywords: markdown,toc,tree,html,mermaid,documentation,converter
Platform: any
Classifier: Development Status :: 4 - Beta
Classifier: Intended Audience :: Developers
Classifier: Intended Audience :: End Users/Desktop
Classifier: License :: OSI Approved :: MIT License
Classifier: Operating System :: OS Independent
Classifier: Programming Language :: Python
Classifier: Programming Language :: Python :: 3
Classifier: Programming Language :: Python :: 3.7
Classifier: Programming Language :: Python :: 3.8
Classifier: Programming Language :: Python :: 3.9
Classifier: Programming Language :: Python :: 3.10
Classifier: Programming Language :: Python :: 3.11
Classifier: Programming Language :: Python :: 3.12
Classifier: Topic :: Internet :: WWW/HTTP :: Dynamic Content
Classifier: Topic :: Software Development :: Libraries :: Python Modules
Classifier: Topic :: Internet :: WWW/HTTP :: Site Management
Classifier: Topic :: Software Development :: Documentation
Classifier: Topic :: Text Processing :: Filters
Classifier: Topic :: Text Processing :: Markup :: HTML
Classifier: Topic :: Text Processing :: Markup :: Markdown
Classifier: Topic :: Utilities
Requires-Python: >=3.7
Requires-Dist: markdown>=3.0
Requires-Dist: pygments>=2.0
Requires-Dist: markdown-mermaidjs>=1.0
Dynamic: author
Dynamic: home-page
Dynamic: platform
Dynamic: requires-python
